powershell/__init__.py
powershell/__version__.py
pypowershell-0.0.1.dev1.dist-info/METADATA
pypowershell-0.0.1.dev1.dist-info/WHEEL
pypowershell-0.0.1.dev1.dist-info/top_level.txt
pypowershell-0.0.1.dev1.dist-info/RECORD
