Metadata-Version: 2.1
Name: pypowershell
Version: 0.0.1.dev1
Summary: Execute PowerShell commands and parse output into native Python objects
Home-page: https://pypowershell.readthedocs.io
Author: ZeroGuard
Author-email: oss@zeroguard.com
License: ZGSL-1.0
Project-URL: Documentation, https://pypowershell.readthedocs.io
Project-URL: Source, https://github.com/zeroguard/pypowershell
Classifier: Development Status :: 1 - Planning
Classifier: Intended Audience :: Developers
Classifier: License :: Other/Proprietary License
Classifier: Natural Language :: English
Classifier: Operating System :: POSIX
Classifier: Programming Language :: Python :: 3.10
Classifier: Programming Language :: Python :: 3.11
Classifier: Topic :: Software Development :: Libraries
Classifier: Topic :: System :: Systems Administration
Requires-Python: >=3.10
Requires-Dist: beartype (==0.11.0)
Requires-Dist: semantic-version (==2.10.0)
